facemarks/__init__.py
facemarks/_geometry_processing.py
facemarks/_mp_utils.py
facemarks/_triangles.py
facemarks/io_utils.py
facemarks/predict.py
facemarks/rendering.py
facemarks-0.4.0.dist-info/licenses/LICENSE
facemarks-0.4.0.dist-info/METADATA
facemarks-0.4.0.dist-info/WHEEL
facemarks-0.4.0.dist-info/top_level.txt
facemarks-0.4.0.dist-info/RECORD
