Metadata-Version: 2.4
Name: facemarks
Version: 0.4.0
Summary: Prediction of 3d facemarks on a 3d face mesh.
Requires-Python: ==3.11.*
License-File: LICENSE
Requires-Dist: mediapipe>=0.10.21
Requires-Dist: open3d==0.18.0
Dynamic: license-file
